pylywsdxx/__init__.py
pylywsdxx/device.py
pylywsdxx/manager.py
pylywsdxx/py.typed
pylywsdxx/radioctl.py
pylywsdxx-2.8.3.dist-info/METADATA
pylywsdxx-2.8.3.dist-info/WHEEL
pylywsdxx-2.8.3.dist-info/licenses/LICENSE
pylywsdxx-2.8.3.dist-info/RECORD
