Metadata-Version: 2.4
Name: pylywsdxx
Version: 2.8.3
Summary: A Python3 class to interrogate Xiaomi Mijia LYWSD* sensors.
Project-URL: Homepage, https://github.com/Mausy5043/pylywsdxx
Project-URL: Bug Tracker, https://github.com/Mausy5043/pylywsdxx/issues
Author: Mausy5043
License-Expression: MIT
License-File: LICENSE
Classifier: Development Status :: 5 - Production/Stable
Classifier: License :: OSI Approved :: MIT License
Classifier: Operating System :: OS Independent
Classifier: Programming Language :: Python :: 3.9
Classifier: Programming Language :: Python :: 3.10
Classifier: Programming Language :: Python :: 3.11
Classifier: Programming Language :: Python :: 3.12
Classifier: Programming Language :: Python :: 3.13
Classifier: Topic :: Home Automation
Requires-Python: >=3.9
Requires-Dist: bluepy3==2.22.3
Requires-Dist: typing-extensions
